Metadata-Version: 2.1
Name: TEST-KEY
Version: 0.0.1
Author: User
License: MIT License
License-File: LICENSE
Requires-Dist: openai==0.28
